trio_binance/__init__.py
trio_binance/client.py
trio_binance/enums.py
trio_binance/exceptions.py
trio_binance/helpers.py
trio_binance/streams.py
trio_binance-0.4.6.dist-info/licenses/LICENSE
trio_binance-0.4.6.dist-info/METADATA
trio_binance-0.4.6.dist-info/WHEEL
trio_binance-0.4.6.dist-info/top_level.txt
trio_binance-0.4.6.dist-info/RECORD
