Metadata-Version: 2.4
Name: trio-binance
Version: 0.4.6
Summary: trio based asynchronous binance SDK
Author-email: Shu Wang <halfelf.ronin@gmail.com>
License-Expression: MIT
Project-URL: Repository, https://github.com/halfelf/trio-binance
Classifier: Framework :: Trio
Classifier: Intended Audience :: Developers
Classifier: Intended Audience :: Financial and Insurance Industry
Requires-Python: >=3.11
License-File: LICENSE
Requires-Dist: h2>=4.1.0
Requires-Dist: httpx>=0.20.0
Requires-Dist: trio>=0.25.0
Requires-Dist: trio-websocket>=0.11.1
Requires-Dist: orjson>=3.6.0
Requires-Dist: pytz>=2024.1
Requires-Dist: dateparser>=1.1.0
Requires-Dist: cryptography>=42.0.7
Dynamic: license-file
